pytest_playwright_json/__init__.py
pytest_playwright_json/attachments.py
pytest_playwright_json/collector.py
pytest_playwright_json/merge.py
pytest_playwright_json/models.py
pytest_playwright_json/plugin.py
pytest_playwright_json-0.1.4.dist-info/METADATA
pytest_playwright_json-0.1.4.dist-info/WHEEL
pytest_playwright_json-0.1.4.dist-info/entry_points.txt
pytest_playwright_json-0.1.4.dist-info/top_level.txt
pytest_playwright_json-0.1.4.dist-info/RECORD
