Metadata-Version: 2.4
Name: pytest-playwright-json
Version: 0.1.4
Summary: Generate Playwright-compatible JSON reports from pytest-playwright test runs
Author-email: TestDino <support@testdino.com>
License: MIT
Project-URL: Homepage, https://github.com/testdino-hq/pytest-playwright-json
Project-URL: Documentation, https://docs.testdino.com/pytest-plugin
Project-URL: Repository, https://github.com/testdino-hq/pytest-playwright-json
Keywords: pytest,playwright,json,report,testing
Classifier: Development Status :: 4 - Beta
Classifier: Framework :: Pytest
Classifier: Intended Audience :: Developers
Classifier: License :: OSI Approved :: MIT License
Classifier: Operating System :: OS Independent
Classifier: Programming Language :: Python :: 3
Classifier: Programming Language :: Python :: 3.9
Classifier: Programming Language :: Python :: 3.10
Classifier: Programming Language :: Python :: 3.11
Classifier: Programming Language :: Python :: 3.12
Classifier: Topic :: Software Development :: Testing
Requires-Python: >=3.9
Requires-Dist: pytest>=7.0.0
Requires-Dist: pydantic>=2.0.0
Provides-Extra: dev
Requires-Dist: pytest-playwright>=0.4.0; extra == "dev"
Requires-Dist: playwright>=1.40.0; extra == "dev"
